offgrid/__init__.py
offgrid/agent.py
offgrid/audio.py
offgrid/client.py
offgrid/kb.py
offgrid/loading.py
offgrid/lora.py
offgrid/models.py
offgrid/p2p.py
offgrid-0.2.11.dist-info/METADATA
offgrid-0.2.11.dist-info/WHEEL
offgrid-0.2.11.dist-info/top_level.txt
offgrid-0.2.11.dist-info/RECORD
