Metadata-Version: 2.1
Name: offgrid
Version: 0.2.11
Summary: Python client for OffGrid LLM - Run AI models completely offline
Author-email: OffGrid LLM Team <team@offgrid-llm.dev>
Maintainer-email: OffGrid LLM Team <team@offgrid-llm.dev>
License: MIT
Project-URL: Homepage, https://github.com/takuphilchan/offgrid-llm
Project-URL: Documentation, https://github.com/takuphilchan/offgrid-llm/tree/main/python
Project-URL: Repository, https://github.com/takuphilchan/offgrid-llm
Project-URL: Issues, https://github.com/takuphilchan/offgrid-llm/issues
Keywords: llm,ai,offline,local,inference,llama,gguf,machine-learning,nlp,chatbot
Classifier: Development Status :: 4 - Beta
Classifier: Intended Audience :: Developers
Classifier: Intended Audience :: Science/Research
Classifier: License :: OSI Approved :: MIT License
Classifier: Operating System :: OS Independent
Classifier: Programming Language :: Python :: 3
Classifier: Programming Language :: Python :: 3.8
Classifier: Programming Language :: Python :: 3.9
Classifier: Programming Language :: Python :: 3.10
Classifier: Programming Language :: Python :: 3.11
Classifier: Programming Language :: Python :: 3.12
Classifier: Topic :: Scientific/Engineering :: Artificial Intelligence
Classifier: Topic :: Software Development :: Libraries :: Python Modules
Requires-Python: >=3.8
Provides-Extra: dev
Requires-Dist: pytest>=7.0; extra == "dev"
Requires-Dist: pytest-cov>=4.0; extra == "dev"
Requires-Dist: black>=23.0; extra == "dev"
Requires-Dist: isort>=5.0; extra == "dev"
Requires-Dist: mypy>=1.0; extra == "dev"
